dojima/__init__.py
dojima/brokers/__init__.py
dojima/brokers/ledgerx.py
dojima/main.py
dojima-0.1.0.dist-info/LICENSE
dojima-0.1.0.dist-info/WHEEL
dojima-0.1.0.dist-info/METADATA
dojima-0.1.0.dist-info/RECORD
