Metadata-Version: 2.1
Name: dojima
Version: 0.1.0
Summary: an interface for crypto derivative apisb
Author: Rahul
Author-email: haxdds@gmail.com
Requires-Python: >=3.8,<4.0
Classifier: Programming Language :: Python :: 3
Classifier: Programming Language :: Python :: 3.10
Classifier: Programming Language :: Python :: 3.8
Classifier: Programming Language :: Python :: 3.9
Requires-Dist: black (>=22.3.0,<23.0.0)
